pymobird.py
pymobird-0.2.1.dist-info/LICENSE
pymobird-0.2.1.dist-info/METADATA
pymobird-0.2.1.dist-info/WHEEL
pymobird-0.2.1.dist-info/top_level.txt
pymobird-0.2.1.dist-info/RECORD
